botwfstools/__init__.py
botwfstools/_version.py
botwfstools/botw_contentfs.py
botwfstools/botw_edit.py
botwfstools/botw_overlayfs.py
botwfstools/botw_patcher.py
botwfstools-1.4.5.dist-info/LICENSE
botwfstools-1.4.5.dist-info/METADATA
botwfstools-1.4.5.dist-info/WHEEL
botwfstools-1.4.5.dist-info/entry_points.txt
botwfstools-1.4.5.dist-info/top_level.txt
botwfstools-1.4.5.dist-info/RECORD
