Metadata-Version: 2.1
Name: botwfstools
Version: 1.4.5
Summary: Tools for exploring and editing Breath of the Wild's ROM
Home-page: https://github.com/leoetlino/botwfstools
Author: leoetlino
Author-email: leo@leolam.fr
License: UNKNOWN
Platform: UNKNOWN
Classifier: License :: OSI Approved :: GNU General Public License v2 or later (GPLv2+)
Classifier: Operating System :: OS Independent
Classifier: Programming Language :: Python :: 3 :: Only
Requires-Python: >=3.6
Requires-Dist: colorama (~=0.4)
Requires-Dist: oead (~=1.0)
Requires-Dist: rstb (~=1.0)
Requires-Dist: sarc (~=2.0)
